homestock/__init__.py
homestock/acs_tables.csv
homestock/cli.py
homestock/common.py
homestock/folium_map.py
homestock/homestock.py
homestock-1.6.8.dist-info/licenses/AUTHORS.rst
homestock-1.6.8.dist-info/licenses/LICENSE
homestock-1.6.8.dist-info/METADATA
homestock-1.6.8.dist-info/WHEEL
homestock-1.6.8.dist-info/entry_points.txt
homestock-1.6.8.dist-info/top_level.txt
homestock-1.6.8.dist-info/RECORD
