Metadata-Version: 2.4
Name: homestock
Version: 1.6.8
Summary: homestock scrapes US Census Bureau data to calculate attainable housing stock for each census tract within a selected county.
Author-email: Joshua Pepper <jepepper19@gmail.com>
License: MIT License
Project-URL: Homepage, https://github.com/jpepper19/homestock
Keywords: homestock
Classifier: Intended Audience :: Developers
Classifier: License :: OSI Approved :: MIT License
Classifier: Natural Language :: English
Classifier: Programming Language :: Python :: 3.8
Classifier: Programming Language :: Python :: 3.9
Classifier: Programming Language :: Python :: 3.10
Classifier: Programming Language :: Python :: 3.11
Classifier: Programming Language :: Python :: 3.12
Requires-Python: >=3.8
License-File: LICENSE
License-File: AUTHORS.rst
Requires-Dist: black
Requires-Dist: black[jupyter]
Requires-Dist: build
Requires-Dist: bump-my-version
Requires-Dist: census
Requires-Dist: click
Requires-Dist: codespell
Requires-Dist: flake8
Requires-Dist: folium
Requires-Dist: geopandas
Requires-Dist: ipykernel
Requires-Dist: ipyleaflet
Requires-Dist: ipywidgets
Requires-Dist: livereload
Requires-Dist: localtileserver
Requires-Dist: matplotlib
Requires-Dist: mkdocs
Requires-Dist: mkdocs-git-revision-date-localized-plugin
Requires-Dist: mkdocs-git-revision-date-plugin
Requires-Dist: mkdocs-jupyter>=0.24.0
Requires-Dist: mkdocs-material>=9.1.3
Requires-Dist: mkdocs-pdf-export-plugin
Requires-Dist: mkdocstrings==0.28.2
Requires-Dist: mkdocstrings-crystal
Requires-Dist: mkdocstrings-python-legacy
Requires-Dist: nbconvert
Requires-Dist: nbformat
Requires-Dist: numpy
Requires-Dist: pygments
Requires-Dist: pymdown-extensions
Requires-Dist: pytest>=7.0.0
Requires-Dist: pytest-runner
Requires-Dist: rasterio
Requires-Dist: requests
Requires-Dist: setuptools
Requires-Dist: sphinx
Requires-Dist: tabulate
Requires-Dist: twine
Requires-Dist: us
Requires-Dist: watchdog
Requires-Dist: wheel
Provides-Extra: all
Requires-Dist: homestock[extra]; extra == "all"
Provides-Extra: extra
Requires-Dist: pandas; extra == "extra"
Dynamic: license-file
